abi2fastq
