Metadata-Version: 1.1
Name: abi2fastq
Version: 1.0.2
Summary: abi2fastq is a small utility to convert Sanger sequencing reads in .abi (applied biosystems) format to FASTQ Edit
Home-page: https://github.com/olgabot/abi2fastq
Author: olgabot
Author-email: olga.botvinnik@gmail.com
License: MIT
Platform: UNKNOWN
Classifier: License :: OSI Approved :: MIT License
Classifier: Natural Language :: English
Classifier: Programming Language :: Python :: 2
Classifier: Programming Language :: Python :: 2.7
Classifier: Programming Language :: Python :: 3
Classifier: Programming Language :: Python :: 3.4
Classifier: Programming Language :: Python :: 3.5
Classifier: Programming Language :: Python :: 3.5
